sheikh_cli/__init__.py
sheikh_cli/main.py
sheikh_cli/run_agent.py
sheikh_cli/tools/__init__.py
sheikh_cli/tools/code_search.py
sheikh_cli/tools/file_operations.py
sheikh_cli/tools/git_operations.py
sheikh_cli/tools/shell_commands.py
sheikh_cli-1.0.0.dist-info/METADATA
sheikh_cli-1.0.0.dist-info/WHEEL
sheikh_cli-1.0.0.dist-info/entry_points.txt
sheikh_cli-1.0.0.dist-info/top_level.txt
sheikh_cli-1.0.0.dist-info/RECORD
