Metadata-Version: 2.4
Name: sheikh-cli
Version: 1.0.0
Summary: Privacy-first AI coding assistant for Termux
Author: osamabinlikhon
License: MIT
Project-URL: Homepage, https://github.com/osamabinlikhon/sheikh-cli
Project-URL: Repository, https://github.com/osamabinlikhon/sheikh-cli
Project-URL: Documentation, https://github.com/osamabinlikhon/sheikh-cli/blob/main/README.md
Project-URL: Bug Tracker, https://github.com/osamabinlikhon/sheikh-cli/issues
Project-URL: Changelog, https://github.com/osamabinlikhon/sheikh-cli/blob/main/CHANGELOG.md
Project-URL: Author, https://github.com/osamabinlikhon
Keywords: termux,coding,assistant,ai,cli,development,android,privacy,local,automation
Classifier: Development Status :: 5 - Production/Stable
Classifier: Environment :: Console
Classifier: Intended Audience :: Developers
Classifier: License :: OSI Approved :: MIT License
Classifier: Operating System :: OS Independent
Classifier: Programming Language :: Python :: 3
Classifier: Programming Language :: Python :: 3.8
Classifier: Programming Language :: Python :: 3.9
Classifier: Programming Language :: Python :: 3.10
Classifier: Programming Language :: Python :: 3.11
Classifier: Programming Language :: Python :: 3.12
Classifier: Topic :: Software Development :: Libraries :: Python Modules
Classifier: Topic :: Software Development :: Code Generators
Classifier: Topic :: Utilities
Requires-Python: >=3.8
Requires-Dist: typer>=0.9.0
Requires-Dist: rich>=13.0.0
Requires-Dist: pydantic>=2.0.0
Requires-Dist: aiofiles>=23.0.0
Requires-Dist: pathspec>=0.11.0
Provides-Extra: dev
Requires-Dist: pytest>=7.4.0; extra == "dev"
Requires-Dist: pytest-asyncio>=0.21.0; extra == "dev"
Requires-Dist: pytest-cov>=4.1.0; extra == "dev"
Requires-Dist: black>=23.0.0; extra == "dev"
Requires-Dist: flake8>=6.0.0; extra == "dev"
Requires-Dist: mypy>=1.0.0; extra == "dev"
